posNegEvolution/__init__.py
posNegEvolution/__main__.py
posNegEvolution/externalPlots.py
posNegEvolution/mainView.py
posNegEvolution/pos_neg_analytical_model.py
posNegEvolution/pos_neg_evolution_init.py
posNegEvolution/pos_neg_evolution_loop.py
posNegEvolution/pos_neg_evolution_loop_VAF.py
posNegEvolution/pos_neg_evolution_loop_one_effect.py
posNegEvolution/wmean.py
posNegEvolution/workspace.py
posNegEvolution-0.1.4.dist-info/LICENSE
posNegEvolution-0.1.4.dist-info/METADATA
posNegEvolution-0.1.4.dist-info/WHEEL
posNegEvolution-0.1.4.dist-info/entry_points.txt
posNegEvolution-0.1.4.dist-info/top_level.txt
posNegEvolution-0.1.4.dist-info/RECORD
