Metadata-Version: 2.1
Name: posNegEvolution
Version: 0.1.4
Summary: Software for simulating positive and negative effect mutations inpact on population evolution in tau leap version.
Home-page: https://github.com/JGil-polsl/posNegEvolution
Author: Jaroslaw Gil
Author-email: jaroslaw.gil@polsl.pl
Project-URL: Bug Reports, https://github.com/JGil-polsl/posNegEvolution/issues
Project-URL: Source, https://github.com/JGil-polsl/posNegEvolution
Keywords: clonal evolution,microbial,numerical modelling
Classifier: Development Status :: 3 - Alpha
Classifier: License :: OSI Approved :: GNU Affero General Public License v3
Classifier: Programming Language :: Python :: 3
Classifier: Programming Language :: Python :: 3.7
Classifier: Programming Language :: Python :: 3.8
Classifier: Programming Language :: Python :: 3.9
Classifier: Programming Language :: Python :: 3.10
Classifier: Programming Language :: Python :: 3 :: Only
Requires-Python: >=3.7
License-File: LICENSE
Requires-Dist: numpy
Requires-Dist: pandas
Requires-Dist: matplotlib
Requires-Dist: PyQt5
Requires-Dist: scipy
